driven/__init__.py
driven/_cobra_ext.py
driven/config.py
driven/stats.py
driven/utils.py
driven/data_sets/__init__.py
driven/data_sets/expression_profile.py
driven/data_sets/fluxes.py
driven/data_sets/normalization.py
driven/data_sets/pax_db.py
driven/flux_analysis/__init__.py
driven/flux_analysis/c13.py
driven/flux_analysis/fluxomics.py
driven/flux_analysis/metrics.py
driven/flux_analysis/profiling.py
driven/flux_analysis/proteomics.py
driven/flux_analysis/results.py
driven/flux_analysis/thermodynamics.py
driven/flux_analysis/tn_seq.py
driven/flux_analysis/transcriptomics.py
driven/flux_analysis/fit_objective/__init__.py
driven/flux_analysis/fit_objective/evaluators.py
driven/flux_analysis/fit_objective/generators.py
driven/flux_analysis/fit_objective/optimization.py
driven/flux_analysis/fit_objective/variators.py
driven/generic/__init__.py
driven/generic/normalization.py
driven/network_analysis/__init__.py
driven/sensitivity_analysis/__init__.py
driven/sensitivity_analysis/flux_analysis.py
driven/vizualization/__init__.py
driven/vizualization/escher_viewer.py
driven/vizualization/utils.py
driven/vizualization/plotting/__init__.py
driven/vizualization/plotting/abstract.py
driven/vizualization/plotting/with_bokeh.py
driven/vizualization/plotting/with_ggplot.py
driven/vizualization/plotting/with_plotly.py
driven-0.0.3.dist-info/DESCRIPTION.rst
driven-0.0.3.dist-info/METADATA
driven-0.0.3.dist-info/RECORD
driven-0.0.3.dist-info/WHEEL
driven-0.0.3.dist-info/metadata.json
driven-0.0.3.dist-info/pbr.json
driven-0.0.3.dist-info/top_level.txt
