Metadata-Version: 2.0
Name: driven
Version: 0.0.3
Summary: driven - data-driven constraint-based analysis
Home-page: http://driven.bio
Author: Joao Cardoso
Author-email: jooaaoo@gmail.com
License: Apache License Version 2.0
Keywords: biology metabolism bioinformatics high-throughput omics
Platform: UNKNOWN
Classifier: Development Status :: 4 - Beta
Classifier: Intended Audience :: Education
Classifier: Intended Audience :: Healthcare Industry
Classifier: Intended Audience :: Science/Research
Classifier: Topic :: Scientific/Engineering :: Bio-Informatics
Classifier: Topic :: Utilities
Classifier: Programming Language :: Python :: 2.6
Classifier: Programming Language :: Python :: 2.7
Classifier: Programming Language :: Python :: 3.4
Classifier: License :: OSI Approved :: Apache Software License
Requires-Dist: bokeh (>=0.11.0)
Requires-Dist: cameo (>=0.7)
Requires-Dist: cobra (>=0.4)
Requires-Dist: ipython (>=4.0)
Requires-Dist: ipywidgets (>=4.0)
Requires-Dist: lxml (>=3.4.4)
Requires-Dist: numpy (>=1.9.2)
Requires-Dist: pandas (>=0.16.2)
Requires-Dist: pyzmq (>=14.5)
Requires-Dist: six (>=1.9.0)
Requires-Dist: sympy (>=0.7.5)
